django_rss_xml
